EAB_tools/__init__.py
EAB_tools/conftest.py
EAB_tools/eab_rc.py
EAB_tools/_testing/__init__.py
EAB_tools/_testing/context_managers.py
EAB_tools/_testing/data_generation.py
EAB_tools/_testing/io.py
EAB_tools/_testing/types.py
EAB_tools/_testing/test_scripts/generate_all_test_data.py
EAB_tools/_testing/test_scripts/generate_fake_enrollments.py
EAB_tools/io/__init__.py
EAB_tools/io/display.py
EAB_tools/io/enrollment.py
EAB_tools/io/filenames.py
EAB_tools/io/io.py
EAB_tools/tests/__init__.py
EAB_tools/tests/_testing/test_data_generation.py
EAB_tools/tests/io/test_display.py
EAB_tools/tests/io/test_enrollment.py
EAB_tools/tests/io/test_filenames.py
EAB_tools/tests/io/test_io.py
EAB_tools/tests/util/test_hashing.py
EAB_tools/util/__init__.py
EAB_tools/util/hashing.py
EAB_tools-0.1.3.2.dist-info/LICENSE
EAB_tools-0.1.3.2.dist-info/METADATA
EAB_tools-0.1.3.2.dist-info/WHEEL
EAB_tools-0.1.3.2.dist-info/top_level.txt
EAB_tools-0.1.3.2.dist-info/RECORD
