Metadata-Version: 2.1
Name: EAB_tools
Version: 0.1.3.2
Summary: Tools for analyzing data exported from the EAB Navigate Student Success Management Software.
Author: Moshe Rubin
Author-email: Moshe Rubin <mosherubin137@gmail.com>
License: MIT License
Project-URL: Homepage, https://github.com/moshemoshe137/EAB_tools
Project-URL: Bug Tracker, https://github.com/moshemoshe137/EAB_tools/issues
Classifier: Development Status :: 1 - Planning
Classifier: Framework :: Jupyter
Classifier: Intended Audience :: Education
Classifier: License :: OSI Approved :: MIT License
Classifier: Operating System :: OS Independent
Classifier: Programming Language :: Python :: 3 :: Only
Classifier: Programming Language :: Python :: 3
Classifier: Topic :: Database
Requires-Python: >=3.9
License-File: LICENSE
Requires-Dist: dataframe-image
Requires-Dist: ipython
Requires-Dist: matplotlib
Requires-Dist: pandas
Provides-Extra: progress_bar
Requires-Dist: tqdm ; extra == 'progress_bar'
